LICENSE.md
MANIFEST.in
setup.py
phoneme_guesser/__init__.py
phoneme_guesser/exceptions.py
phoneme_guesser/utils.py
phoneme_guesser.egg-info/PKG-INFO
phoneme_guesser.egg-info/SOURCES.txt
phoneme_guesser.egg-info/dependency_links.txt
phoneme_guesser.egg-info/top_level.txt
phoneme_guesser/res/ca-es.dict
phoneme_guesser/res/de.dict
phoneme_guesser/res/en-us.dict
phoneme_guesser/res/es-mx.dict
phoneme_guesser/res/es.dict
phoneme_guesser/res/fr.dict
phoneme_guesser/res/it.dict
phoneme_guesser/res/nl.dict
phoneme_guesser/res/pt-br.dict