Metadata-Version: 2.1
Name: phoneme_guesser
Version: 0.1.1
Summary: phonemes from text
Home-page: https://github.com/OpenJarbas/phoneme_guesser
Author: jarbasAi
Author-email: jarbasai@mailfence.com
License: Apache2
Platform: UNKNOWN
License-File: LICENSE.md
